MANIFEST.in
README.rst
setup.cfg
setup.py
datafiles/.DS_Store
datafiles/aws-cli-menu.yml
datafiles/scripts/.DS_Store
datafiles/scripts/accept_peering_connections.py
datafiles/scripts/add_network_acl_entry.py
datafiles/scripts/allocate_address_for_elastic_ip.py
datafiles/scripts/associate_dhcp_option_to_vpc.py
datafiles/scripts/associate_elastic_ip.py
datafiles/scripts/associate_route_table_to_subnet.py
datafiles/scripts/attach_instance_to_elastic_load_balancer.py
datafiles/scripts/attach_internet_gateway.py
datafiles/scripts/attach_network_interface.py
datafiles/scripts/attach_policy_from_user.py
datafiles/scripts/attach_policy_to_group.py
datafiles/scripts/attach_policy_to_role.py
datafiles/scripts/attach_policy_to_user.py
datafiles/scripts/attach_volume.py
datafiles/scripts/authorize_rds_security_group_ingress.py
datafiles/scripts/change_map_public_ip_on_launch_for_subnet.py
datafiles/scripts/change_network_acl_subnet_association.py
datafiles/scripts/change_rds_security_group.py
datafiles/scripts/copy_shared_rds_snapshot.py
datafiles/scripts/create_cf_stack.py
datafiles/scripts/create_cloud_watch_alarm.py
datafiles/scripts/create_customer_gateway.py
datafiles/scripts/create_dhcp_option.py
datafiles/scripts/create_dynamodb_table.py
datafiles/scripts/create_ecs_auto_scaling_group.py
datafiles/scripts/create_ecs_cluster.py
datafiles/scripts/create_ecs_instance.py
datafiles/scripts/create_ecs_instance_role.py
datafiles/scripts/create_ecs_launch_configuration.py
datafiles/scripts/create_ecs_security_group.py
datafiles/scripts/create_ecs_service.py
datafiles/scripts/create_ecs_service_role.py
datafiles/scripts/create_elastic_cache_cluster.py
datafiles/scripts/create_elastic_cache_parameter_group.py
datafiles/scripts/create_elastic_cache_replication_group.py
datafiles/scripts/create_elastic_cache_security_group.py
datafiles/scripts/create_elastic_cache_subnet_group.py
datafiles/scripts/create_elastic_ip.py
datafiles/scripts/create_elastic_load_balancer.py
src/aws_cli_menu.egg-info/PKG-INFO
src/aws_cli_menu.egg-info/SOURCES.txt
src/aws_cli_menu.egg-info/dependency_links.txt
src/aws_cli_menu.egg-info/entry_points.txt
src/aws_cli_menu.egg-info/requires.txt
src/aws_cli_menu.egg-info/top_level.txt
