Metadata-Version: 1.1
Name: aws-cli-menu
Version: 0.4.45
Summary: Menu system for Managing AWS Accounts
Home-page: https://rubelw@bitbucket.org/rubelw/aws_cli_menu.git
Author: Will Rubel
Author-email: willrubel@gmail.com
License: Apache 2.0 License
Keywords: AWS CLI AWSCLI Boto Boto3
Platform: UNKNOWN
Classifier: Development Status :: 4 - Beta
Classifier: Operating System :: POSIX
Classifier: Operating System :: MacOS :: MacOS X
Classifier: Intended Audience :: Developers
Classifier: Intended Audience :: System Administrators
Classifier: Intended Audience :: Information Technology
Classifier: License :: OSI Approved :: Apache Software License
Classifier: Natural Language :: English
Classifier: Programming Language :: Python :: 2.7
Classifier: Topic :: System :: Systems Administration
